hamilton_lsp/__init__.py
hamilton_lsp/__main__.py
hamilton_lsp/server.py
sf_hamilton_lsp-0.1.0.dist-info/METADATA
sf_hamilton_lsp-0.1.0.dist-info/WHEEL
sf_hamilton_lsp-0.1.0.dist-info/entry_points.txt
sf_hamilton_lsp-0.1.0.dist-info/top_level.txt
sf_hamilton_lsp-0.1.0.dist-info/RECORD
